{
  "metro_id": 948,
  "test_rmse": 10.4161,
  "test_r_squared": 0.2321,
  "train_rmse": 10.4172,
  "train_r_squared": 0.2526,
  "residual_standard_error_default": 10.4161,
  "standard_error_method": "Residual SD on held-out test split by day_of_week/hour_of_day; fallback to test RMSE.",
  "standard_error_by_hour_day": [
    {
      "day_of_week": 1,
      "hour_of_day": 9,
      "standard_error": 12.2123,
      "n": 13
    },
    {
      "day_of_week": 4,
      "hour_of_day": 12,
      "standard_error": 13.0288,
      "n": 9
    },
    {
      "day_of_week": 7,
      "hour_of_day": 2,
      "standard_error": 3.6674,
      "n": 16
    },
    {
      "day_of_week": 7,
      "hour_of_day": 3,
      "standard_error": 6.2152,
      "n": 12
    },
    {
      "day_of_week": 7,
      "hour_of_day": 4,
      "standard_error": 5.5253,
      "n": 16
    },
    {
      "day_of_week": 1,
      "hour_of_day": 1,
      "standard_error": 3.0957,
      "n": 4
    },
    {
      "day_of_week": 1,
      "hour_of_day": 2,
      "standard_error": 5.1803,
      "n": 14
    },
    {
      "day_of_week": 1,
      "hour_of_day": 3,
      "standard_error": 10.2632,
      "n": 3
    },
    {
      "day_of_week": 1,
      "hour_of_day": 4,
      "standard_error": 9.1844,
      "n": 18
    },
    {
      "day_of_week": 1,
      "hour_of_day": 6,
      "standard_error": 6.9426,
      "n": 5
    },
    {
      "day_of_week": 1,
      "hour_of_day": 7,
      "standard_error": 10.3777,
      "n": 12
    },
    {
      "day_of_week": 1,
      "hour_of_day": 11,
      "standard_error": 10.9079,
      "n": 8
    },
    {
      "day_of_week": 1,
      "hour_of_day": 12,
      "standard_error": 10.8025,
      "n": 9
    },
    {
      "day_of_week": 1,
      "hour_of_day": 13,
      "standard_error": 11.0992,
      "n": 13
    },
    {
      "day_of_week": 1,
      "hour_of_day": 15,
      "standard_error": 13.2877,
      "n": 13
    },
    {
      "day_of_week": 1,
      "hour_of_day": 16,
      "standard_error": 8.9038,
      "n": 9
    },
    {
      "day_of_week": 1,
      "hour_of_day": 17,
      "standard_error": 13.3118,
      "n": 22
    },
    {
      "day_of_week": 1,
      "hour_of_day": 18,
      "standard_error": 9.9243,
      "n": 11
    },
    {
      "day_of_week": 1,
      "hour_of_day": 19,
      "standard_error": 7.2045,
      "n": 7
    },
    {
      "day_of_week": 1,
      "hour_of_day": 20,
      "standard_error": 9.7496,
      "n": 11
    },
    {
      "day_of_week": 1,
      "hour_of_day": 21,
      "standard_error": 9.6177,
      "n": 9
    },
    {
      "day_of_week": 1,
      "hour_of_day": 22,
      "standard_error": 3.4779,
      "n": 17
    },
    {
      "day_of_week": 1,
      "hour_of_day": 23,
      "standard_error": 2.582,
      "n": 7
    },
    {
      "day_of_week": 2,
      "hour_of_day": 0,
      "standard_error": 1.075,
      "n": 10
    },
    {
      "day_of_week": 2,
      "hour_of_day": 1,
      "standard_error": 1.5492,
      "n": 10
    },
    {
      "day_of_week": 2,
      "hour_of_day": 4,
      "standard_error": 14.27,
      "n": 18
    },
    {
      "day_of_week": 2,
      "hour_of_day": 6,
      "standard_error": 11.709,
      "n": 6
    },
    {
      "day_of_week": 2,
      "hour_of_day": 7,
      "standard_error": 14.27,
      "n": 14
    },
    {
      "day_of_week": 2,
      "hour_of_day": 9,
      "standard_error": 12.2656,
      "n": 19
    },
    {
      "day_of_week": 2,
      "hour_of_day": 11,
      "standard_error": 12.772,
      "n": 8
    },
    {
      "day_of_week": 2,
      "hour_of_day": 13,
      "standard_error": 11.1222,
      "n": 18
    },
    {
      "day_of_week": 2,
      "hour_of_day": 15,
      "standard_error": 11.9615,
      "n": 13
    },
    {
      "day_of_week": 2,
      "hour_of_day": 17,
      "standard_error": 9.6338,
      "n": 18
    },
    {
      "day_of_week": 2,
      "hour_of_day": 18,
      "standard_error": 8.5412,
      "n": 7
    },
    {
      "day_of_week": 2,
      "hour_of_day": 19,
      "standard_error": 11.1749,
      "n": 12
    },
    {
      "day_of_week": 2,
      "hour_of_day": 20,
      "standard_error": 9.539,
      "n": 12
    },
    {
      "day_of_week": 2,
      "hour_of_day": 21,
      "standard_error": 6.1644,
      "n": 18
    },
    {
      "day_of_week": 2,
      "hour_of_day": 22,
      "standard_error": 6.4506,
      "n": 17
    },
    {
      "day_of_week": 3,
      "hour_of_day": 1,
      "standard_error": 1.2774,
      "n": 14
    },
    {
      "day_of_week": 3,
      "hour_of_day": 4,
      "standard_error": 10.988,
      "n": 20
    },
    {
      "day_of_week": 3,
      "hour_of_day": 7,
      "standard_error": 11.8181,
      "n": 13
    },
    {
      "day_of_week": 3,
      "hour_of_day": 9,
      "standard_error": 12.077,
      "n": 11
    },
    {
      "day_of_week": 3,
      "hour_of_day": 11,
      "standard_error": 8.2416,
      "n": 15
    },
    {
      "day_of_week": 3,
      "hour_of_day": 12,
      "standard_error": 15.7147,
      "n": 7
    },
    {
      "day_of_week": 3,
      "hour_of_day": 13,
      "standard_error": 8.0995,
      "n": 13
    },
    {
      "day_of_week": 3,
      "hour_of_day": 15,
      "standard_error": 7.1877,
      "n": 16
    },
    {
      "day_of_week": 3,
      "hour_of_day": 16,
      "standard_error": 10.3296,
      "n": 5
    },
    {
      "day_of_week": 3,
      "hour_of_day": 17,
      "standard_error": 14.6143,
      "n": 13
    },
    {
      "day_of_week": 3,
      "hour_of_day": 18,
      "standard_error": 5.2328,
      "n": 17
    },
    {
      "day_of_week": 3,
      "hour_of_day": 19,
      "standard_error": 10.2897,
      "n": 10
    },
    {
      "day_of_week": 3,
      "hour_of_day": 20,
      "standard_error": 9.4664,
      "n": 22
    },
    {
      "day_of_week": 3,
      "hour_of_day": 21,
      "standard_error": 4.5751,
      "n": 12
    },
    {
      "day_of_week": 3,
      "hour_of_day": 22,
      "standard_error": 6.1845,
      "n": 21
    },
    {
      "day_of_week": 4,
      "hour_of_day": 1,
      "standard_error": 0.7188,
      "n": 16
    },
    {
      "day_of_week": 4,
      "hour_of_day": 4,
      "standard_error": 12.107,
      "n": 24
    },
    {
      "day_of_week": 4,
      "hour_of_day": 7,
      "standard_error": 11.7848,
      "n": 17
    },
    {
      "day_of_week": 4,
      "hour_of_day": 9,
      "standard_error": 11.9593,
      "n": 13
    },
    {
      "day_of_week": 4,
      "hour_of_day": 11,
      "standard_error": 16.8708,
      "n": 10
    },
    {
      "day_of_week": 4,
      "hour_of_day": 13,
      "standard_error": 11.714,
      "n": 11
    },
    {
      "day_of_week": 4,
      "hour_of_day": 15,
      "standard_error": 0,
      "n": 2
    },
    {
      "day_of_week": 4,
      "hour_of_day": 16,
      "standard_error": 17.2905,
      "n": 16
    },
    {
      "day_of_week": 4,
      "hour_of_day": 18,
      "standard_error": 16.2069,
      "n": 16
    },
    {
      "day_of_week": 4,
      "hour_of_day": 19,
      "standard_error": 7.3275,
      "n": 13
    },
    {
      "day_of_week": 4,
      "hour_of_day": 20,
      "standard_error": 10.3231,
      "n": 6
    },
    {
      "day_of_week": 4,
      "hour_of_day": 21,
      "standard_error": 7.3759,
      "n": 17
    },
    {
      "day_of_week": 4,
      "hour_of_day": 22,
      "standard_error": 7.5892,
      "n": 22
    },
    {
      "day_of_week": 5,
      "hour_of_day": 14,
      "standard_error": 10.3751,
      "n": 8
    },
    {
      "day_of_week": 5,
      "hour_of_day": 15,
      "standard_error": 9.2075,
      "n": 9
    },
    {
      "day_of_week": 5,
      "hour_of_day": 16,
      "standard_error": 12.7822,
      "n": 14
    },
    {
      "day_of_week": 5,
      "hour_of_day": 17,
      "standard_error": 12.4987,
      "n": 11
    },
    {
      "day_of_week": 5,
      "hour_of_day": 18,
      "standard_error": 8.1737,
      "n": 7
    },
    {
      "day_of_week": 5,
      "hour_of_day": 19,
      "standard_error": 10.9575,
      "n": 17
    },
    {
      "day_of_week": 5,
      "hour_of_day": 20,
      "standard_error": 6.313,
      "n": 11
    },
    {
      "day_of_week": 5,
      "hour_of_day": 21,
      "standard_error": 9.4371,
      "n": 17
    },
    {
      "day_of_week": 5,
      "hour_of_day": 22,
      "standard_error": 4.8679,
      "n": 8
    },
    {
      "day_of_week": 6,
      "hour_of_day": 1,
      "standard_error": 6.4568,
      "n": 11
    },
    {
      "day_of_week": 6,
      "hour_of_day": 4,
      "standard_error": 3.5119,
      "n": 7
    },
    {
      "day_of_week": 6,
      "hour_of_day": 6,
      "standard_error": 8.3103,
      "n": 12
    },
    {
      "day_of_week": 6,
      "hour_of_day": 8,
      "standard_error": 12.145,
      "n": 13
    },
    {
      "day_of_week": 6,
      "hour_of_day": 10,
      "standard_error": 13.1933,
      "n": 16
    },
    {
      "day_of_week": 6,
      "hour_of_day": 11,
      "standard_error": 10.882,
      "n": 14
    },
    {
      "day_of_week": 6,
      "hour_of_day": 13,
      "standard_error": 12.2027,
      "n": 7
    },
    {
      "day_of_week": 6,
      "hour_of_day": 14,
      "standard_error": 12.3722,
      "n": 8
    },
    {
      "day_of_week": 6,
      "hour_of_day": 15,
      "standard_error": 14.4289,
      "n": 13
    },
    {
      "day_of_week": 6,
      "hour_of_day": 16,
      "standard_error": 14.3819,
      "n": 15
    },
    {
      "day_of_week": 6,
      "hour_of_day": 17,
      "standard_error": 9.8333,
      "n": 9
    },
    {
      "day_of_week": 6,
      "hour_of_day": 18,
      "standard_error": 4.9552,
      "n": 8
    },
    {
      "day_of_week": 6,
      "hour_of_day": 19,
      "standard_error": 8.5184,
      "n": 11
    },
    {
      "day_of_week": 6,
      "hour_of_day": 20,
      "standard_error": 12.1977,
      "n": 16
    },
    {
      "day_of_week": 6,
      "hour_of_day": 21,
      "standard_error": 8.5698,
      "n": 18
    },
    {
      "day_of_week": 6,
      "hour_of_day": 22,
      "standard_error": 6.649,
      "n": 15
    },
    {
      "day_of_week": 6,
      "hour_of_day": 23,
      "standard_error": 10.4858,
      "n": 7
    },
    {
      "day_of_week": 7,
      "hour_of_day": 6,
      "standard_error": 2.7538,
      "n": 4
    },
    {
      "day_of_week": 7,
      "hour_of_day": 8,
      "standard_error": 8.0416,
      "n": 6
    },
    {
      "day_of_week": 7,
      "hour_of_day": 9,
      "standard_error": 10.3725,
      "n": 13
    },
    {
      "day_of_week": 7,
      "hour_of_day": 10,
      "standard_error": 11.8157,
      "n": 9
    },
    {
      "day_of_week": 7,
      "hour_of_day": 11,
      "standard_error": 16.5937,
      "n": 15
    },
    {
      "day_of_week": 7,
      "hour_of_day": 13,
      "standard_error": 16.9189,
      "n": 4
    },
    {
      "day_of_week": 7,
      "hour_of_day": 14,
      "standard_error": 13.4932,
      "n": 16
    },
    {
      "day_of_week": 7,
      "hour_of_day": 15,
      "standard_error": 9.434,
      "n": 9
    },
    {
      "day_of_week": 7,
      "hour_of_day": 16,
      "standard_error": 6.7725,
      "n": 6
    },
    {
      "day_of_week": 7,
      "hour_of_day": 17,
      "standard_error": 11.0064,
      "n": 13
    },
    {
      "day_of_week": 7,
      "hour_of_day": 18,
      "standard_error": 14.3429,
      "n": 12
    },
    {
      "day_of_week": 7,
      "hour_of_day": 19,
      "standard_error": 8.7017,
      "n": 12
    },
    {
      "day_of_week": 7,
      "hour_of_day": 20,
      "standard_error": 9.1658,
      "n": 10
    },
    {
      "day_of_week": 7,
      "hour_of_day": 21,
      "standard_error": 7.2446,
      "n": 20
    },
    {
      "day_of_week": 7,
      "hour_of_day": 22,
      "standard_error": 4.2817,
      "n": 12
    },
    {
      "day_of_week": 7,
      "hour_of_day": 23,
      "standard_error": 5.2589,
      "n": 10
    },
    {
      "day_of_week": 1,
      "hour_of_day": 0,
      "standard_error": 1.472,
      "n": 6
    },
    {
      "day_of_week": 2,
      "hour_of_day": 10,
      "standard_error": 11.2368,
      "n": 6
    },
    {
      "day_of_week": 2,
      "hour_of_day": 12,
      "standard_error": 10.0167,
      "n": 4
    },
    {
      "day_of_week": 2,
      "hour_of_day": 14,
      "standard_error": 0,
      "n": 2
    },
    {
      "day_of_week": 2,
      "hour_of_day": 23,
      "standard_error": 1.1547,
      "n": 3
    },
    {
      "day_of_week": 4,
      "hour_of_day": 10,
      "standard_error": 10.3078,
      "n": 4
    },
    {
      "day_of_week": 4,
      "hour_of_day": 14,
      "standard_error": 8.9672,
      "n": 8
    },
    {
      "day_of_week": 4,
      "hour_of_day": 23,
      "standard_error": 2.0412,
      "n": 6
    },
    {
      "day_of_week": 5,
      "hour_of_day": 0,
      "standard_error": 3.6742,
      "n": 6
    },
    {
      "day_of_week": 5,
      "hour_of_day": 3,
      "standard_error": 10.8781,
      "n": 4
    },
    {
      "day_of_week": 5,
      "hour_of_day": 5,
      "standard_error": 7.4322,
      "n": 7
    },
    {
      "day_of_week": 5,
      "hour_of_day": 7,
      "standard_error": 10.1887,
      "n": 7
    },
    {
      "day_of_week": 5,
      "hour_of_day": 8,
      "standard_error": 15.174,
      "n": 4
    },
    {
      "day_of_week": 5,
      "hour_of_day": 10,
      "standard_error": 13.0448,
      "n": 6
    },
    {
      "day_of_week": 5,
      "hour_of_day": 11,
      "standard_error": 14.8391,
      "n": 5
    },
    {
      "day_of_week": 5,
      "hour_of_day": 13,
      "standard_error": 12.8335,
      "n": 5
    },
    {
      "day_of_week": 6,
      "hour_of_day": 9,
      "standard_error": 10.6748,
      "n": 7
    },
    {
      "day_of_week": 6,
      "hour_of_day": 12,
      "standard_error": 12.5399,
      "n": 9
    },
    {
      "day_of_week": 7,
      "hour_of_day": 1,
      "standard_error": 3.0957,
      "n": 4
    },
    {
      "day_of_week": 7,
      "hour_of_day": 7,
      "standard_error": 9.8995,
      "n": 5
    },
    {
      "day_of_week": 7,
      "hour_of_day": 12,
      "standard_error": 8.2624,
      "n": 8
    }
  ]
}
